{
  "required": true,
  "minVersion": "0.8",
  "package": "com.ptsmods.morecommands.client.mixin",
  "compatibilityLevel": "JAVA_16",
  "plugin": "com.ptsmods.morecommands.MixinPlugin",
  "client": [
    "MixinAbstractBlock",
    "MixinAbstractClientPlayerEntity",
    "MixinAnvilScreen",
    "MixinBiome",
    "MixinBookEditScreen",
    "MixinCactusBlock",
    "MixinChatScreen",
    "MixinClickableWidget",
    "MixinClickEventAction",
    "MixinClientPacketListener",
    "MixinClientPlayerEntity",
    "MixinClientPlayerEntityTweakerooCompat",
    "MixinClientPlayerInteractionManager",
    "MixinCreativeInventoryScreen",
    "MixinEntity",
    "MixinEntityCallbacks",
    "MixinEntityRenderer",
    "MixinGameRenderer",
    "MixinGuiMessage",
    "MixinHandledScreen",
    "MixinInGameHud",
    "MixinInventoryScreen",
    "MixinItemModelGenerator",
    "MixinItemRenderer",
    "MixinKeyboard",
    "MixinLanguage",
    "MixinLivingEntityRenderer",
    "MixinMinecraft",
    "MixinModelLoader",
    "MixinMoreOptionsDialog",
    "MixinMouse",
    "MixinOptionsScreen",
    "MixinParticleManager",
    "MixinPlayerEntity",
    "MixinPlayerEntityModel",
    "MixinPlayerListHud",
    "MixinPlayerRenderer",
    "MixinRuleListVisitor",
    "MixinScreen",
    "MixinSignEditScreen",
    "MixinStyle",
    "MixinSuspiciousStewItem",
    "MixinTextColor",
    "MixinTextVisitFactory",
    "MixinTitleScreen",
    "accessor.MixinClickableWidgetAccessor",
    "accessor.MixinCommandSuggestorAccessor",
    "accessor.MixinEntitySelectorAccessor",
    "accessor.MixinJsonUnbakedModelAccessor",
    "accessor.MixinMapColorAccessor",
    "accessor.MixinMinecraftClientAccessor",
    "accessor.MixinMouseAccessor",
    "accessor.MixinParticleManagerAccessor",
    "accessor.MixinStyleAccessor",
    "accessor.MixinSuggestionWindowAccessor",
    "accessor.MixinWindowAccessor"
  ],
  "injectors": {
    "defaultRequire": 1
  }
}
